{
  "toolscriptVersion": "1.0.0",
  "version": "43.0.9",
  "pageUuid": "00000000-0000-0000-0000-000000000001",
  "appTemplate": {
    "appMaxWidth": "100%",
    "appThemeId": -1,
    "experimentalFeatures": {
      "object": {
        "sourceControlTemplateDehydration": false
      }
    },
    "notificationsSettings": {
      "object": {
        "globalQueryShowFailureToast": true,
        "globalQueryShowSuccessToast": true,
        "globalQueryToastDuration": 4.5
      }
    },
    "version": "3.338.0"
  }
}
